igwas-0.1.0.dist-info/METADATA
igwas-0.1.0.dist-info/WHEEL
igwas-0.1.0.dist-info/licenses/LICENSE
igwas/test_igwas.py
igwas/__init__.py
igwas/igwas.py
igwas/_lowlevel.cpython-312-darwin.so
igwas-0.1.0.dist-info/RECORD
