Metadata-Version: 2.3
Name: igwas
Version: 0.1.0
Requires-Dist: pandas >=2.2.2
Requires-Dist: numpy >=2.1.0
Requires-Dist: zstandard >=0.23.0
License-File: LICENSE
Summary: Add your description here
Author-email: zietzm <michael.zietz@gmail.com>
Requires-Python: >=3.10
